README.md
setup.cfg
setup.py
pytorch_hed.egg-info/PKG-INFO
pytorch_hed.egg-info/SOURCES.txt
pytorch_hed.egg-info/dependency_links.txt
pytorch_hed.egg-info/entry_points.txt
pytorch_hed.egg-info/not-zip-safe
pytorch_hed.egg-info/top_level.txt
torchHED/__init__.py
torchHED/__version__.py
torchHED/hed.py
torchHED/network.py