Metadata-Version: 2.1
Name: pytorch-hed
Version: 0.5
Summary: pytorch-hed - Holistically-Nested Edge Detection based on Pytorch
Home-page: https://github.com/Davidelanz/pytorch-hed
Author: Davide Lanza
Author-email: lanza.davide.it@gmail.com
License: GNU General Public License v3.0
Keywords: edge-detection pytorch
Platform: UNKNOWN
Classifier: Intended Audience :: Developers
Classifier: Programming Language :: Python :: 3.7
Classifier: License :: OSI Approved :: GNU General Public License (GPL)
Classifier: Natural Language :: English
Requires-Python: >=3.7.*
